accountant/__init__.py
accountant/client.py
common/__init__.py
common/cs_enum.py
ledger/__init__.py
ledger/client.py
tests/__init__.py
tests/accountant_test.py
accountant-1.1.14.dist-info/METADATA
accountant-1.1.14.dist-info/WHEEL
accountant-1.1.14.dist-info/top_level.txt
accountant-1.1.14.dist-info/RECORD
