Metadata-Version: 2.1
Name: accountant
Version: 1.1.14
Summary: Accountant package
Home-page: https://github.com/pypa/sampleproject
Author: prakhar
Author-email: author@example.com
License: UNKNOWN
Platform: UNKNOWN
Classifier: Programming Language :: Python :: 3
Classifier: License :: OSI Approved :: MIT License
Classifier: Operating System :: OS Independent
Requires-Python: >=3.6
Requires-Dist: jsonrpcclient (>=0.1.1)
Requires-Dist: typing (>=3.6)
Requires-Dist: requests (>=2.22.0)
